[
  {
    "id": "example",
    "name": "示例",
    "type": "此处填写类型",
    "version": "此处填写版本",
    "icon": "https://mcjpg.org/logo.png",
    "description": "此处填写描述",
    "link": "https://mcjpg.org",
    "ip": "mcjpg.org"
  },
  {
    "id": "1",
    "name": "1",
    "type": "1",
    "version": "1",
    "icon": "https://mcjpg.org/logo_AI.png",
    "link": "https://mcjpg.org/logo_AI.png",
    "description": "1"
  },
  {
    "id": "2",
    "name": "1",
    "type": "1",
    "version": "1",
    "icon": "https://mcjpg.org/logo_AI.png",
    "link": "https://mcjpg.org/logo_AI.png",
    "description": "1"
  },
  {
    "id": "3",
    "name": "1",
    "type": "1",
    "version": "1",
    "icon": "https://mcjpg.org/logo_AI.png",
    "link": "https://mcjpg.org/logo_AI.png",
    "description": "1"
  },
  {
    "id": "4",
    "name": "1",
    "type": "1",
    "version": "1",
    "icon": "https://mcjpg.org/logo_AI.png",
    "link": "https://mcjpg.org/logo_AI.png",
    "description": "1"
  }
]